autalac_de2v2/__init__.py
autalac_de2v2/main.py
autalac_de2v2-0.1.0.dist-info/METADATA
autalac_de2v2-0.1.0.dist-info/WHEEL
autalac_de2v2-0.1.0.dist-info/RECORD
