Metadata-Version: 2.1
Name: autalac_de2v2
Version: 0.1.0
Summary: POC python library for Turing college
Author: AugTal
Author-email: augustas.talacka@gmail.com
Requires-Python: >=3.11,<4.0
Classifier: Programming Language :: Python :: 3
Classifier: Programming Language :: Python :: 3.11
Classifier: Programming Language :: Python :: 3.12
Requires-Dist: numpy (>=1.26.4,<2.0.0)
